twitton/__init__.py
twitton/tweet_search_api.py
twitton-1.0.0.dist-info/DESCRIPTION.rst
twitton-1.0.0.dist-info/METADATA
twitton-1.0.0.dist-info/RECORD
twitton-1.0.0.dist-info/WHEEL
twitton-1.0.0.dist-info/metadata.json
twitton-1.0.0.dist-info/top_level.txt
