Metadata-Version: 2.0
Name: twitton
Version: 1.0.0
Summary: A simple Data Scraping library for Twitter API
Home-page: https://github.com/marcosvbras/twitton
Author: Marcos Vinícius Brás
Author-email: marcosvbras@gmail.com
License: Apache
Download-URL: https://github.com/marcosvbras/twitton
Keywords: data twitter search scraping api
Platform: UNKNOWN
Classifier: Development Status :: 4 - Beta
Classifier: Environment :: Web Environment
Classifier: Intended Audience :: Developers
Classifier: License :: OSI Approved :: Apache Software License
Classifier: Natural Language :: English
Classifier: Operating System :: OS Independent
Classifier: Programming Language :: Python :: 3.6
Classifier: Topic :: Internet
Classifier: Topic :: Software Development :: Libraries :: Python Modules
Requires-Python: ~=3.6
Requires-Dist: certifi (==2018.1.18)
Requires-Dist: chardet (==3.0.4)
Requires-Dist: idna (==2.6)
Requires-Dist: oauthlib (==2.0.6)
Requires-Dist: requests (==2.18.4)
Requires-Dist: requests-oauthlib (==0.8.0)
Requires-Dist: urllib3 (==1.22)
